COPYING
MANIFEST.in
README.rst
distribute_setup.py
rdt_requirements
setup.py
Orange_Multitarget.egg-info/PKG-INFO
Orange_Multitarget.egg-info/SOURCES.txt
Orange_Multitarget.egg-info/dependency_links.txt
Orange_Multitarget.egg-info/entry_points.txt
Orange_Multitarget.egg-info/not-zip-safe
Orange_Multitarget.egg-info/requires.txt
Orange_Multitarget.egg-info/top_level.txt
_multitarget/__init__.py
_multitarget/binary.py
_multitarget/chain.py
_multitarget/neural.py
_multitarget/pls.py
_multitarget/scoring.py
_multitarget/tree.py
_multitarget/datasets/bridges.tab
_multitarget/datasets/emotions.tab
_multitarget/datasets/flare.tab
_multitarget/widgets/OWBinaryRelevance.py
_multitarget/widgets/OWClassifierChain.py
_multitarget/widgets/OWClusteringRandomForest.py
_multitarget/widgets/OWClusteringTree.py
_multitarget/widgets/OWEnsembleClassifierChain.py
_multitarget/widgets/OWNeuralNetwork.py
_multitarget/widgets/OWPLSClassifier.py
_multitarget/widgets/OWTestMultitargetLearners.py
_multitarget/widgets/__init__.py
_multitarget/widgets/icons/BinaryRelevance.png
_multitarget/widgets/icons/ClassifierChain.png
_multitarget/widgets/icons/ClusteringRandomForest.png
_multitarget/widgets/icons/ClusteringTree.png
_multitarget/widgets/icons/EnsembleClassifierChain.png
_multitarget/widgets/icons/NeuralNetwork.png
_multitarget/widgets/icons/PLSClassification.png
_multitarget/widgets/icons/TestMTLearners.png
docs/Makefile
docs/rst/BinaryRelevance.rst
docs/rst/ClassifierChain.rst
docs/rst/ClusteringRandomForest.rst
docs/rst/ClusteringTree.rst
docs/rst/EnsembleClassifierChains.rst
docs/rst/NeuralNetwork.rst
docs/rst/Orange.multitarget.binary.rst
docs/rst/Orange.multitarget.chain.rst
docs/rst/Orange.multitarget.neural.rst
docs/rst/Orange.multitarget.pls.rst
docs/rst/Orange.multitarget.rst
docs/rst/Orange.multitarget.scoring.rst
docs/rst/Orange.multitarget.tree.rst
docs/rst/Orange.regression.earth.rst
docs/rst/PLSClassification.rst
docs/rst/TestMultitargetLearners.rst
docs/rst/conf.py
docs/rst/index.rst
docs/rst/code/binary.py
docs/rst/code/chain.py
docs/rst/code/clustering_tree.py
docs/rst/code/earth.py
docs/rst/code/generate_multitarget.py
docs/rst/code/mt-evaluate.py
docs/rst/code/multitarget.py
docs/rst/code/neural.py
docs/rst/code/pls-example.py
docs/rst/code/pls.py
